{"state":"ok","message":"","special":"","vipMessage":"","isLogin":0,"data":{"nodes":[{"id":"793450635","labels":["Company"],"properties":{"ntype":"s","name":"克拉玛依融信智有信息技术有限责任公司"}},{"id":"2173782617","labels":["Human"],"properties":{"ntype":"s","name":"谈继强"}},{"id":"2311219467","labels":["Company"],"properties":{"ntype":"s","name":"巴州丝路楼兰信息技术有限公司"}},{"id":"2377742386","labels":["Company"],"properties":{"ntype":"f","name":"克拉玛依志同道合股权投资管理有限公司"}},{"id":"2070806563","labels":["Human"],"properties":{"ntype":"f","name":"王怡然"}},{"id":"1786817490","labels":["Human"],"properties":{"ntype":"f","name":"余高林"}},{"id":"1923194226","labels":["Human"],"properties":{"ntype":"f","name":"张国利"}},{"id":"1782544554","labels":["Human"],"properties":{"ntype":"f","name":"何芳"}},{"id":"190212929","labels":["Company"],"properties":{"ntype":"f","name":"新疆同方信息系统工程有限公司"}},{"id":"1909127953","labels":["Human"],"properties":{"ntype":"f","name":"帕哈尔丁"}},{"id":"190213066","labels":["Company"],"properties":{"ntype":"f","name":"新疆威盾电子科技有限公司"}},{"id":"2351144706","labels":["Company"],"properties":{"ntype":"f","name":"克拉玛依红同投资管理合伙企业（有限合伙）"}},{"id":"2283170167","labels":["Human"],"properties":{"ntype":"f","name":"高东"}},{"id":"1938723884","labels":["Human"],"properties":{"ntype":"s","name":"徐亚明"}},{"id":"1946700139","labels":["Human"],"properties":{"ntype":"f","name":"成龙"}},{"id":"352600103","labels":["Company"],"properties":{"ntype":"s","name":"克拉玛依市独山子红有智联信息技术有限责任公司"}},{"id":"190212979","labels":["Company"],"properties":{"ntype":"f","name":"克拉玛依红有软件有限责任公司"}},{"id":"2076970729","labels":["Human"],"properties":{"ntype":"f","name":"王英辉"}},{"id":"2238772441","labels":["Human"],"properties":{"ntype":"s","name":"闫淮岩"}},{"id":"657222471","labels":["Company"],"properties":{"ntype":"s","name":"新疆时讯立维信息技术股份有限公司"}},{"id":"1101625154","labels":["Company"],"properties":{"ntype":"s","name":"克拉玛依有道投资管理合伙企业（有限合伙）"}},{"id":"1890814943","labels":["Human"],"properties":{"ntype":"s","name":"宋江伟"}},{"id":"1926162976","labels":["Human"],"properties":{"ntype":"s","name":"张慧玲"}},{"id":"1101625158","labels":["Company"],"properties":{"ntype":"s","name":"克拉玛依有志投资管理合伙企业（有限合伙）"}},{"id":"2078904856","labels":["Human"],"properties":{"ntype":"f","name":"王陵军"}},{"id":"2225686555","labels":["Human"],"properties":{"ntype":"f","name":"郭本强"}},{"id":"1771631982","labels":["Human"],"properties":{"ntype":"s","name":"仝满霞"}},{"id":"1924255238","labels":["Human"],"properties":{"ntype":"f","name":"张宏"}},{"id":"1902911637","labels":["Human"],"properties":{"ntype":"s","name":"岳虎"}},{"id":"1101625042","labels":["Company"],"properties":{"ntype":"s","name":"红有软件股份有限公司"}},{"id":"190211754","labels":["Company"],"properties":{"ntype":"s","name":"新疆时讯立维信息技术服务有限公司"}},{"id":"2233548383","labels":["Human"],"properties":{"ntype":"s","name":"钟志华"}}],"relationships":[{"id":"285192116","startNode":"2173782617","properties":{"amount":"0.0","labels":["参股"]},"type":"INVEST_H","endNode":"2377742386"},{"id":"148911921","startNode":"2173782617","properties":{"labels":["执行董事"]},"type":"SERVE","endNode":"2377742386"},{"id":"114835334","startNode":"2173782617","properties":{"labels":["法人"]},"type":"OWN","endNode":"2377742386"},{"id":"284629462","startNode":"2377742386","properties":{"labels":["参股"]},"type":"INVEST_C","endNode":"2351144706"},{"id":"84464864","startNode":"2173782617","properties":{"labels":["法人"]},"type":"OWN","endNode":"190212979"},{"id":"161932776","startNode":"2070806563","properties":{"amount":"0.0","labels":["参股"]},"type":"INVEST_H","endNode":"657222471"},{"id":"3791651","startNode":"2173782617","properties":{"amount":"0.0","labels":["参股"]},"type":"INVEST_H","endNode":"1101625154"},{"id":"218391887","startNode":"2377742386","properties":{"amount":"0.0","labels":["参股"]},"type":"INVEST_C","endNode":"1101625154"},{"id":"61263255","startNode":"2377742386","properties":{"labels":["法人"]},"type":"OWN","endNode":"1101625154"},{"id":"270732114","startNode":"2173782617","properties":{"labels":["参股"]},"type":"INVEST_H","endNode":"1101625158"},{"id":"241098018","startNode":"2377742386","properties":{"labels":["参股"]},"type":"INVEST_C","endNode":"1101625158"},{"id":"20277640","startNode":"2173782617","properties":{"amount":"0.0","labels":["参股"]},"type":"INVEST_H","endNode":"1101625042"},{"id":"1029103","startNode":"2173782617","properties":{"labels":["董事长"]},"type":"SERVE","endNode":"1101625042"},{"id":"279243380","startNode":"2173782617","properties":{"labels":["法人"]},"type":"OWN","endNode":"1101625042"},{"id":"217423484","startNode":"2070806563","properties":{"amount":"0.0","labels":["参股"]},"type":"INVEST_H","endNode":"190211754"},{"id":"129788066","startNode":"1786817490","properties":{"labels":["副董事长"]},"type":"SERVE","endNode":"657222471"},{"id":"182161861","startNode":"1786817490","properties":{"amount":"0.0","labels":["参股"]},"type":"INVEST_H","endNode":"657222471"},{"id":"217423486","startNode":"1786817490","properties":{"amount":"0.0","labels":["参股"]},"type":"INVEST_H","endNode":"190211754"},{"id":"199664221","startNode":"1923194226","properties":{"amount":"0.0","labels":["参股"]},"type":"INVEST_H","endNode":"2377742386"},{"id":"114968060","startNode":"1923194226","properties":{"amount":"0.0","labels":["参股"]},"type":"INVEST_H","endNode":"1101625154"},{"id":"270732107","startNode":"1923194226","properties":{"labels":["参股"]},"type":"INVEST_H","endNode":"1101625158"},{"id":"309340219","startNode":"1782544554","properties":{"labels":["董事"]},"type":"SERVE","endNode":"793450635"},{"id":"26167758","startNode":"1782544554","properties":{"amount":"0.0","labels":["参股"]},"type":"INVEST_H","endNode":"2377742386"},{"id":"263153411","startNode":"1782544554","properties":{"labels":["参股"]},"type":"INVEST_H","endNode":"2351144706"},{"id":"270732116","startNode":"1782544554","properties":{"labels":["参股"]},"type":"INVEST_H","endNode":"1101625158"},{"id":"262192227","startNode":"190212929","properties":{"amount":"0.0","labels":["参股"]},"type":"INVEST_C","endNode":"657222471"},{"id":"218739308","startNode":"190212929","properties":{"amount":"0.0","labels":["参股"]},"type":"INVEST_C","endNode":"190211754"},{"id":"93131704","startNode":"1909127953","properties":{"labels":["董事"]},"type":"SERVE","endNode":"657222471"},{"id":"166386780","startNode":"1909127953","properties":{"amount":"0.0","labels":["参股"]},"type":"INVEST_H","endNode":"657222471"},{"id":"217423482","startNode":"1909127953","properties":{"amount":"0.0","labels":["参股"]},"type":"INVEST_H","endNode":"190211754"},{"id":"318171861","startNode":"190213066","properties":{"amount":"0.0","labels":["参股"]},"type":"INVEST_C","endNode":"657222471"},{"id":"152533201","startNode":"190213066","properties":{"amount":"0.0","labels":["参股"]},"type":"INVEST_C","endNode":"190211754"},{"id":"176718854","startNode":"2283170167","properties":{"labels":["董事长兼总经理"]},"type":"SERVE","endNode":"190212929"},{"id":"121411551","startNode":"2283170167","properties":{"labels":["法人"]},"type":"OWN","endNode":"190212929"},{"id":"310768014","startNode":"2283170167","properties":{"amount":"0.0","labels":["参股"]},"type":"INVEST_H","endNode":"190212929"},{"id":"65764846","startNode":"2283170167","properties":{"labels":["董事长"]},"type":"SERVE","endNode":"657222471"},{"id":"11877162","startNode":"2283170167","properties":{"labels":["法人"]},"type":"OWN","endNode":"657222471"},{"id":"119536738","startNode":"2283170167","properties":{"labels":["董事长"]},"type":"SERVE","endNode":"190211754"},{"id":"84468522","startNode":"2283170167","properties":{"labels":["法人"]},"type":"OWN","endNode":"190211754"},{"id":"92608375","startNode":"1938723884","properties":{"amount":"0.0","labels":["参股"]},"type":"INVEST_H","endNode":"2377742386"},{"id":"284154503","startNode":"1938723884","properties":{"labels":["参股"]},"type":"INVEST_H","endNode":"2351144706"},{"id":"242969623","startNode":"1938723884","properties":{"amount":"0.0","labels":["参股"]},"type":"INVEST_H","endNode":"1101625154"},{"id":"3947201","startNode":"1938723884","properties":{"labels":["董事"]},"type":"SERVE","endNode":"1101625042"},{"id":"119536741","startNode":"1938723884","properties":{"labels":["监事"]},"type":"SERVE","endNode":"190211754"},{"id":"266574164","startNode":"1946700139","properties":{"amount":"0.0","labels":["参股"]},"type":"INVEST_H","endNode":"2377742386"},{"id":"62953205","startNode":"1946700139","properties":{"labels":["董事"]},"type":"SERVE","endNode":"657222471"},{"id":"167964989","startNode":"1946700139","properties":{"amount":"0.0","labels":["参股"]},"type":"INVEST_H","endNode":"1101625154"},{"id":"261706783","startNode":"190212979","properties":{"labels":["参股"]},"type":"INVEST_C","endNode":"2311219467"},{"id":"219671626","startNode":"190212979","properties":{"amount":"350.0","labels":["参股"]},"type":"INVEST_C","endNode":"352600103"},{"id":"266601554","startNode":"190212979","properties":{"amount":"0.0","labels":["参股"]},"type":"INVEST_C","endNode":"657222471"},{"id":"217423487","startNode":"190212979","properties":{"amount":"0.0","labels":["参股"]},"type":"INVEST_C","endNode":"190211754"},{"id":"250062227","startNode":"2076970729","properties":{"amount":"0.0","labels":["参股"]},"type":"INVEST_H","endNode":"657222471"},{"id":"217423485","startNode":"2076970729","properties":{"amount":"0.0","labels":["参股"]},"type":"INVEST_H","endNode":"190211754"},{"id":"187465495","startNode":"2238772441","properties":{"amount":"0.0","labels":["参股"]},"type":"INVEST_H","endNode":"2377742386"},{"id":"2464734","startNode":"2238772441","properties":{"labels":["参股"]},"type":"INVEST_H","endNode":"2351144706"},{"id":"270732105","startNode":"2238772441","properties":{"labels":["参股"]},"type":"INVEST_H","endNode":"1101625158"},{"id":"17728621","startNode":"2238772441","properties":{"labels":["董事"]},"type":"SERVE","endNode":"1101625042"},{"id":"38923242","startNode":"1101625154","properties":{"amount":"0.0","labels":["参股"]},"type":"INVEST_C","endNode":"1101625042"},{"id":"122024289","startNode":"1890814943","properties":{"labels":["经理"]},"type":"SERVE","endNode":"2377742386"},{"id":"286158539","startNode":"1890814943","properties":{"amount":"0.0","labels":["参股"]},"type":"INVEST_H","endNode":"2377742386"},{"id":"242969624","startNode":"1890814943","properties":{"amount":"0.0","labels":["参股"]},"type":"INVEST_H","endNode":"1101625154"},{"id":"270732115","startNode":"1890814943","properties":{"labels":["参股"]},"type":"INVEST_H","endNode":"1101625158"},{"id":"309008934","startNode":"1890814943","properties":{"labels":["董事"]},"type":"SERVE","endNode":"1101625042"},{"id":"270732108","startNode":"1926162976","properties":{"labels":["参股"]},"type":"INVEST_H","endNode":"1101625158"},{"id":"5695412","startNode":"1926162976","properties":{"labels":["监事"]},"type":"SERVE","endNode":"1101625042"},{"id":"45006754","startNode":"1101625158","properties":{"amount":"0.0","labels":["参股"]},"type":"INVEST_C","endNode":"1101625042"},{"id":"155273752","startNode":"2078904856","properties":{"labels":["法人"]},"type":"OWN","endNode":"793450635"},{"id":"180270978","startNode":"2078904856","properties":{"labels":["董事长"]},"type":"SERVE","endNode":"793450635"},{"id":"263153412","startNode":"2078904856","properties":{"labels":["参股"]},"type":"INVEST_H","endNode":"2351144706"},{"id":"159173072","startNode":"2078904856","properties":{"amount":"0.0","labels":["参股"]},"type":"INVEST_H","endNode":"1101625154"},{"id":"278562361","startNode":"2225686555","properties":{"amount":"0.0","labels":["参股"]},"type":"INVEST_H","endNode":"1101625154"},{"id":"270732087","startNode":"2225686555","properties":{"labels":["参股"]},"type":"INVEST_H","endNode":"1101625158"},{"id":"187128369","startNode":"1771631982","properties":{"labels":["参股"]},"type":"INVEST_H","endNode":"2351144706"},{"id":"270732091","startNode":"1771631982","properties":{"labels":["参股"]},"type":"INVEST_H","endNode":"1101625158"},{"id":"11640369","startNode":"1771631982","properties":{"labels":["监事"]},"type":"SERVE","endNode":"1101625042"},{"id":"103960380","startNode":"1924255238","properties":{"amount":"0.0","labels":["参股"]},"type":"INVEST_H","endNode":"190212929"},{"id":"273626754","startNode":"1924255238","properties":{"labels":["副董事长"]},"type":"SERVE","endNode":"190212929"},{"id":"158242282","startNode":"1924255238","properties":{"labels":["副董事长"]},"type":"SERVE","endNode":"657222471"},{"id":"182161862","startNode":"1924255238","properties":{"amount":"0.0","labels":["参股"]},"type":"INVEST_H","endNode":"657222471"},{"id":"217423489","startNode":"1924255238","properties":{"amount":"0.0","labels":["参股"]},"type":"INVEST_H","endNode":"190211754"},{"id":"119536740","startNode":"1924255238","properties":{"labels":["董事"]},"type":"SERVE","endNode":"190211754"},{"id":"187917273","startNode":"1902911637","properties":{"labels":["监事"]},"type":"SERVE","endNode":"2377742386"},{"id":"259187425","startNode":"1902911637","properties":{"amount":"0.0","labels":["参股"]},"type":"INVEST_H","endNode":"2377742386"},{"id":"270732103","startNode":"1902911637","properties":{"labels":["参股"]},"type":"INVEST_H","endNode":"1101625158"},{"id":"5041725","startNode":"1902911637","properties":{"labels":["监事会主席"]},"type":"SERVE","endNode":"1101625042"},{"id":"19182617","startNode":"1101625042","properties":{"amount":"0.0","labels":["参股"]},"type":"INVEST_C","endNode":"793450635"},{"id":"17805592","startNode":"1101625042","properties":{"labels":["参股"]},"type":"INVEST_C","endNode":"2311219467"},{"id":"18647140","startNode":"1101625042","properties":{"amount":"350.0","labels":["参股"]},"type":"INVEST_C","endNode":"352600103"},{"id":"18786531","startNode":"1101625042","properties":{"amount":"0.0","labels":["参股"]},"type":"INVEST_C","endNode":"657222471"},{"id":"17738486","startNode":"1101625042","properties":{"amount":"0.0","labels":["参股"]},"type":"INVEST_C","endNode":"190211754"},{"id":"11602026","startNode":"2233548383","properties":{"labels":["董事"]},"type":"SERVE","endNode":"793450635"},{"id":"295483227","startNode":"2233548383","properties":{"amount":"0.0","labels":["参股"]},"type":"INVEST_H","endNode":"2377742386"},{"id":"261035351","startNode":"2233548383","properties":{"labels":["参股"]},"type":"INVEST_H","endNode":"2351144706"},{"id":"158165852","startNode":"2233548383","properties":{"amount":"0.0","labels":["参股"]},"type":"INVEST_H","endNode":"1101625154"},{"id":"270732078","startNode":"2233548383","properties":{"labels":["参股"]},"type":"INVEST_H","endNode":"1101625158"},{"id":"7551206","startNode":"2233548383","properties":{"labels":["董事兼总经理"]},"type":"SERVE","endNode":"1101625042"}]}}